sisplit/__init__.py
sisplit/__main__.py
sisplit/sisplit.py
bbo_pysisplit-1.0.0.dist-info/LICENSE
bbo_pysisplit-1.0.0.dist-info/METADATA
bbo_pysisplit-1.0.0.dist-info/WHEEL
bbo_pysisplit-1.0.0.dist-info/top_level.txt
bbo_pysisplit-1.0.0.dist-info/RECORD
